rutil.py
rutil-0.0.2.dist-info/METADATA
rutil-0.0.2.dist-info/WHEEL
rutil-0.0.2.dist-info/top_level.txt
rutil-0.0.2.dist-info/RECORD
